nexus/__init__.py
nexus/constants.py
nexus/core.py
nexus/exceptions.py
nexus/kem.py
nexus/math_utils.py
nexus/signature.py
nexus_crypt-1.0.0.dist-info/licenses/LICENSE
tests/__init__.py
tests/test_cipher.py
tests/test_integrations.py
tests/test_kem.py
tests/test_math_utils.py
tests/test_signature.py
nexus_crypt-1.0.0.dist-info/METADATA
nexus_crypt-1.0.0.dist-info/WHEEL
nexus_crypt-1.0.0.dist-info/top_level.txt
nexus_crypt-1.0.0.dist-info/RECORD
