Metadata-Version: 2.4
Name: nexus-crypt
Version: 1.0.0
Summary: Post-quantum cryptographic suite with PFS, encryption, signatures, and hashing
Home-page: https://github.com/Harshith2412/nexus-crypt
Author: Harshith Madhavaram
Author-email: madhavaram.harshith2412@gmail.com
Classifier: Development Status :: 4 - Beta
Classifier: Intended Audience :: Developers
Classifier: Topic :: Security :: Cryptography
Classifier: License :: OSI Approved :: MIT License
Classifier: Programming Language :: Python :: 3.8
Classifier: Programming Language :: Python :: 3.9
Classifier: Programming Language :: Python :: 3.10
Classifier: Programming Language :: Python :: 3.11
Requires-Python: >=3.8
License-File: LICENSE
Requires-Dist: pycryptodome>=3.19.0
Requires-Dist: pqcrypto>=0.1.0
Requires-Dist: numpy>=1.24.0
Provides-Extra: dev
Requires-Dist: pytest>=7.0; extra == "dev"
Requires-Dist: black; extra == "dev"
Requires-Dist: mypy; extra == "dev"
Dynamic: author
Dynamic: author-email
Dynamic: classifier
Dynamic: description
Dynamic: description-content-type
Dynamic: home-page
Dynamic: license-file
Dynamic: provides-extra
Dynamic: requires-dist
Dynamic: requires-python
Dynamic: summary
